py3dbp/__init__.py
py3dbp/example.py
py3dbp/main.py
py3dbp-0.3.dist-info/LICENSE
py3dbp-0.3.dist-info/METADATA
py3dbp-0.3.dist-info/WHEEL
py3dbp-0.3.dist-info/top_level.txt
py3dbp-0.3.dist-info/RECORD
