Metadata-Version: 2.1
Name: py3dbp
Version: 0.3
Summary: 3D Bin Packing
Home-page: https://github.com/enzoruiz/3dbinpacking
Author: Enzo Ruiz Pelaez
Author-email: enzo.rp.90@gmail.com
License: UNKNOWN
Platform: UNKNOWN
Classifier: Programming Language :: Python :: 3
Classifier: License :: OSI Approved :: MIT License
Classifier: Operating System :: OS Independent
